foodplate/__init__.py
foodplate/_modidx.py
foodplate/core.py
foodplate-0.0.1.dist-info/LICENSE
foodplate-0.0.1.dist-info/METADATA
foodplate-0.0.1.dist-info/WHEEL
foodplate-0.0.1.dist-info/entry_points.txt
foodplate-0.0.1.dist-info/top_level.txt
foodplate-0.0.1.dist-info/RECORD
